Metadata-Version: 1.0
Name: Products.Zope-Hotfix-20111024
Version: 1.0
Summary: Hotfix for Zope 2.12 + 2.13
Home-page: http://svn.zope.org/Zope/hotfixes/Products.Zope_Hotfix_20111024
Author: Zope Foundation and Contributors
Author-email: zope-dev@zope.org
License: ZPL 2.1
Keywords: security hotfix patch
Platform: UNKNOWN
Classifier: Programming Language :: Python
Classifier: Framework :: Zope2
Classifier: License :: OSI Approved :: Zope Public License
